Termicolor/All.py
Termicolor/Ansi.py
Termicolor/Attributes.py
Termicolor/Background.py
Termicolor/Color.py
Termicolor/Foreground.py
Termicolor/Styles.py
Termicolor/__init__.py
Termicolor-1.1.1.dist-info/LICENSE
Termicolor-1.1.1.dist-info/METADATA
Termicolor-1.1.1.dist-info/WHEEL
Termicolor-1.1.1.dist-info/top_level.txt
Termicolor-1.1.1.dist-info/RECORD
