Metadata-Version: 2.1
Name: Termicolor
Version: 1.1.1
Summary: Simple, intuitive, chainable API for styling and coloring the terminal
Author-email: border-l <border-l@example.com>
Project-URL: Homepage, https://github.com/border-l/Termicolor
Classifier: Development Status :: 4 - Beta
Classifier: Intended Audience :: Developers
Classifier: License :: OSI Approved :: MIT License
Classifier: Programming Language :: Python
Classifier: Operating System :: OS Independent
Classifier: Topic :: Terminals
Classifier: Topic :: Software Development :: Libraries :: Python Modules
Classifier: Topic :: Software Development :: User Interfaces
Requires-Python: >=3.5
License-File: LICENSE
Requires-Dist: colorama >=0.4.4
